tremolo_login/__init__.py
tremolo_login-1.1.1.dist-info/licenses/LICENSE
tremolo_login-1.1.1.dist-info/METADATA
tremolo_login-1.1.1.dist-info/WHEEL
tremolo_login-1.1.1.dist-info/top_level.txt
tremolo_login-1.1.1.dist-info/RECORD
