Metadata-Version: 2.4
Name: tremolo-login
Version: 1.1.1
Summary: tremolo-login is basically an extension of tremolo-session.
Author-email: Anggit Arfanto <contact@anggit.com>
License-Expression: MIT
Project-URL: Homepage, https://github.com/nggit/tremolo-login
Project-URL: Source, https://github.com/nggit/tremolo-login
Project-URL: Funding, https://github.com/sponsors/nggit
Classifier: Development Status :: 4 - Beta
Classifier: Intended Audience :: Developers
Classifier: Operating System :: OS Independent
Classifier: Topic :: Software Development :: Libraries :: Application Frameworks
Requires-Python: >=3.6
License-File: LICENSE
Requires-Dist: tremolo>=0.5.0
Dynamic: license-file
